ukis_metrics/__init__.py
ukis_metrics/seg_metrics.py
ukis_metrics-0.1.4.dist-info/LICENSE
ukis_metrics-0.1.4.dist-info/METADATA
ukis_metrics-0.1.4.dist-info/WHEEL
ukis_metrics-0.1.4.dist-info/RECORD
