Metadata-Version: 2.1
Name: ukis-metrics
Version: 0.1.4
Summary: Numpy-based implementation of common performance metrics for semantic image segmentation
Home-page: https://github.com/dlr-eoc/ukis-metrics
License: Apache 2.0
Author: German Aerospace Center (DLR)
Author-email: ukis-helpdesk@dlr.de
Requires-Python: >=3.8,<4.0
Classifier: License :: Other/Proprietary License
Classifier: Programming Language :: Python :: 3
Classifier: Programming Language :: Python :: 3.8
Classifier: Programming Language :: Python :: 3.9
Classifier: Programming Language :: Python :: 3.10
Classifier: Programming Language :: Python :: 3.11
Requires-Dist: numpy (>=1.24.3,<2.0.0)
Project-URL: Repository, https://github.com/dlr-eoc/ukis-metrics
